pymin_reqs/__init__.py
pymin_reqs/pymin_reqs.py
pymin_reqs-1.0.2.dist-info/LICENSE
pymin_reqs-1.0.2.dist-info/METADATA
pymin_reqs-1.0.2.dist-info/WHEEL
pymin_reqs-1.0.2.dist-info/entry_points.txt
pymin_reqs-1.0.2.dist-info/top_level.txt
pymin_reqs-1.0.2.dist-info/RECORD
