Metadata-Version: 2.1
Name: pymin-reqs
Version: 1.0.2
Summary: Create a minimal requirements.txt file from Python source code
Home-page: https://github.com/parnell/pymin-reqs
Author: Parnell
Author-email: 
License: UNKNOWN
Platform: UNKNOWN
Classifier: Programming Language :: Python :: 3
Classifier: License :: OSI Approved :: MIT License
Classifier: Operating System :: OS Independent
Requires-Dist: pip (>=20.0)
